CHANGELOG.txt
LICENSE
MANIFEST.in
README.md
pyproject.toml
setup.py
Plotium/__init__.py
Plotium.egg-info/PKG-INFO
Plotium.egg-info/SOURCES.txt
Plotium.egg-info/dependency_links.txt
Plotium.egg-info/requires.txt
Plotium.egg-info/top_level.txt
Plotium/Blocks/__init__.py
Plotium/Blocks/D_BLOCK/__init__.py
Plotium/Blocks/D_BLOCK/atomic_radius.py
Plotium/Blocks/D_BLOCK/boiling_point.py
Plotium/Blocks/D_BLOCK/const.py
Plotium/Blocks/D_BLOCK/density.py
Plotium/Blocks/D_BLOCK/electronegativity.py
Plotium/Blocks/D_BLOCK/melting_point.py
Plotium/Blocks/F_BLOCK/__init__.py
Plotium/Blocks/F_BLOCK/atomic_radius.py
Plotium/Blocks/F_BLOCK/boiling_point.py
Plotium/Blocks/F_BLOCK/const.py
Plotium/Blocks/F_BLOCK/density.py
Plotium/Blocks/F_BLOCK/electronegativity.py
Plotium/Blocks/F_BLOCK/melting_point.py
Plotium/Blocks/P_BLOCK/__init__.py
Plotium/Blocks/P_BLOCK/atomic_radius.py
Plotium/Blocks/P_BLOCK/boiling_point.py
Plotium/Blocks/P_BLOCK/const.py
Plotium/Blocks/P_BLOCK/density.py
Plotium/Blocks/P_BLOCK/electronegativity.py
Plotium/Blocks/P_BLOCK/melting_point.py
Plotium/Blocks/S_BLOCK/__init__.py
Plotium/Blocks/S_BLOCK/atomic_radius.py
Plotium/Blocks/S_BLOCK/boiling_point.py
Plotium/Blocks/S_BLOCK/const.py
Plotium/Blocks/S_BLOCK/density.py
Plotium/Blocks/S_BLOCK/electronegativity.py
Plotium/Blocks/S_BLOCK/melting_point.py
Plotium/Group/__init__.py
Plotium/Group/GROUP_1/__init__.py
Plotium/Group/GROUP_1/atomic_radius.py
Plotium/Group/GROUP_1/boiling_point.py
Plotium/Group/GROUP_1/const.py
Plotium/Group/GROUP_1/density.py
Plotium/Group/GROUP_1/electronegativity.py
Plotium/Group/GROUP_1/melting_point.py
Plotium/Group/GROUP_10/__init__.py
Plotium/Group/GROUP_10/atomic_radius.py
Plotium/Group/GROUP_10/boiling_point.py
Plotium/Group/GROUP_10/const.py
Plotium/Group/GROUP_10/density.py
Plotium/Group/GROUP_10/electronegativity.py
Plotium/Group/GROUP_10/melting_point.py
Plotium/Group/GROUP_11/__init__.py
Plotium/Group/GROUP_11/atomic_radius.py
Plotium/Group/GROUP_11/boiling_point.py
Plotium/Group/GROUP_11/const.py
Plotium/Group/GROUP_11/density.py
Plotium/Group/GROUP_11/electronegativity.py
Plotium/Group/GROUP_11/melting_point.py
venv/Lib/site-packages/backports.tarfile-1.2.0.dist-info/top_level.txt
venv/Lib/site-packages/certifi-2024.7.4.dist-info/top_level.txt
venv/Lib/site-packages/charset_normalizer-3.3.2.dist-info/entry_points.txt
venv/Lib/site-packages/charset_normalizer-3.3.2.dist-info/top_level.txt
venv/Lib/site-packages/cycler-0.12.1.dist-info/top_level.txt
venv/Lib/site-packages/docutils-0.21.2.dist-info/COPYING.txt
venv/Lib/site-packages/docutils-0.21.2.dist-info/entry_points.txt
venv/Lib/site-packages/fonttools-4.53.0.dist-info/entry_points.txt
venv/Lib/site-packages/fonttools-4.53.0.dist-info/top_level.txt
venv/Lib/site-packages/importlib_metadata-8.0.0.dist-info/top_level.txt
venv/Lib/site-packages/jaraco.classes-3.4.0.dist-info/top_level.txt
venv/Lib/site-packages/jaraco.context-5.3.0.dist-info/top_level.txt
venv/Lib/site-packages/jaraco.functools-4.0.1.dist-info/top_level.txt
venv/Lib/site-packages/keyring-25.2.1.dist-info/entry_points.txt
venv/Lib/site-packages/keyring-25.2.1.dist-info/top_level.txt
venv/Lib/site-packages/kiwisolver-1.4.5.dist-info/top_level.txt
venv/Lib/site-packages/markdown_it_py-3.0.0.dist-info/entry_points.txt
venv/Lib/site-packages/numpy-2.0.0.dist-info/LICENSE.txt
venv/Lib/site-packages/numpy-2.0.0.dist-info/entry_points.txt
venv/Lib/site-packages/pillow-10.4.0.dist-info/top_level.txt
venv/Lib/site-packages/pip-22.3.1.dist-info/LICENSE.txt
venv/Lib/site-packages/pip-22.3.1.dist-info/entry_points.txt
venv/Lib/site-packages/pip-22.3.1.dist-info/top_level.txt
venv/Lib/site-packages/pkginfo-1.10.0.dist-info/LICENSE.txt
venv/Lib/site-packages/pkginfo-1.10.0.dist-info/entry_points.txt
venv/Lib/site-packages/pkginfo-1.10.0.dist-info/top_level.txt
venv/Lib/site-packages/pygments-2.18.0.dist-info/entry_points.txt
venv/Lib/site-packages/python_dateutil-2.9.0.post0.dist-info/top_level.txt
venv/Lib/site-packages/pywin32_ctypes-0.2.2.dist-info/LICENSE.txt
venv/Lib/site-packages/pywin32_ctypes-0.2.2.dist-info/top_level.txt
venv/Lib/site-packages/readme_renderer-43.0.dist-info/top_level.txt
venv/Lib/site-packages/requests-2.32.3.dist-info/top_level.txt
venv/Lib/site-packages/requests_toolbelt-1.0.0.dist-info/top_level.txt
venv/Lib/site-packages/rfc3986-2.0.0.dist-info/top_level.txt
venv/Lib/site-packages/setuptools-65.5.1.dist-info/entry_points.txt
venv/Lib/site-packages/setuptools-65.5.1.dist-info/top_level.txt
venv/Lib/site-packages/six-1.16.0.dist-info/top_level.txt
venv/Lib/site-packages/twine-5.1.1.dist-info/entry_points.txt
venv/Lib/site-packages/twine-5.1.1.dist-info/top_level.txt
venv/Lib/site-packages/urllib3-2.2.2.dist-info/licenses/LICENSE.txt
venv/Lib/site-packages/wheel-0.38.4.dist-info/LICENSE.txt
venv/Lib/site-packages/wheel-0.38.4.dist-info/entry_points.txt
venv/Lib/site-packages/wheel-0.38.4.dist-info/top_level.txt
venv/Lib/site-packages/zipp-3.19.2.dist-info/top_level.txt
