Metadata-Version: 2.1
Name: Plotium
Version: 1.2.0
Summary: Python Library to plot and visualize chemical trends
Home-page: https://github.com/rohankishore/Plotium
Author: Rohan Kishore
Author-email: rohankishore746@outlook.com
License: MIT
Keywords: calculator,chemistry,chemical plots
Classifier: Development Status :: 5 - Production/Stable
Classifier: Intended Audience :: Education
Classifier: Operating System :: Microsoft :: Windows :: Windows 11
Classifier: License :: OSI Approved :: MIT License
Classifier: Programming Language :: Python :: 3
License-File: LICENSE
